mypackage/__init__.py
mypackage/main.py
stiko-0.0.1.dist-info/LICENSE.txt
stiko-0.0.1.dist-info/METADATA
stiko-0.0.1.dist-info/WHEEL
stiko-0.0.1.dist-info/top_level.txt
stiko-0.0.1.dist-info/RECORD
