Metadata-Version: 2.1
Name: stiko
Version: 0.0.1
Summary: Keyless Cryptography Algorithm
Home-page: https://github.com/pypa/sampleproject
Author: Prateek Yadav
Author-email: yprateek658@gmail.com
License: UNKNOWN
Project-URL: Bug Tracker, https://github.com/pypa/sampleproject/issues
Platform: UNKNOWN
Classifier: Programming Language :: Python :: 3
Classifier: License :: OSI Approved :: MIT License
Classifier: Operating System :: OS Independent
Requires-Python: >=3.6
License-File: LICENSE.txt
